sphinx_graph/__init__.py
sphinx_graph/config.py
sphinx_graph/formatting.py
sphinx_graph/parse.py
sphinx_graph/util.py
sphinx_graph/table/__init__.py
sphinx_graph/table/directive.py
sphinx_graph/table/events.py
sphinx_graph/table/info.py
sphinx_graph/table/node.py
sphinx_graph/table/state.py
sphinx_graph/vertex/__init__.py
sphinx_graph/vertex/config.py
sphinx_graph/vertex/directive.py
sphinx_graph/vertex/events.py
sphinx_graph/vertex/info.py
sphinx_graph/vertex/layout.py
sphinx_graph/vertex/node.py
sphinx_graph/vertex/query.py
sphinx_graph/vertex/state.py
sphinx_graph-0.3.3.dist-info/METADATA
sphinx_graph-0.3.3.dist-info/WHEEL
sphinx_graph-0.3.3.dist-info/RECORD
