Metadata-Version: 2.4
Name: sphinx-graph
Version: 0.3.3
Summary: 'Sphinx-Graph' is a plain-text, VCS-friendly, requirements management tool.
Project-URL: Homepage, https://github.com/danieleades/sphinx-graph
Project-URL: Documentation, https://sphinx-graph.readthedocs.io/en/latest/index.html
Author-email: Daniel Eades <danieleades@hotmail.com>
License: MIT
Keywords: documentation,plain-text,sphinx, requirements
Classifier: Development Status :: 4 - Beta
Classifier: Framework :: Sphinx :: Extension
Classifier: Intended Audience :: Developers
Classifier: Intended Audience :: Manufacturing
Classifier: License :: OSI Approved :: MIT License
Classifier: Programming Language :: Python :: 3.10
Classifier: Programming Language :: Python :: 3.11
Classifier: Programming Language :: Python :: 3.12
Classifier: Programming Language :: Python :: 3.13
Classifier: Topic :: Documentation
Classifier: Topic :: Documentation :: Sphinx
Classifier: Topic :: Utilities
Requires-Python: >=3.11
Requires-Dist: rustworkx~=0.17.1
Requires-Dist: sphinx<10,>=7
Requires-Dist: toml~=0.10.2
